[{"action":{"redirect":{"extensionPath":"/success.html"},"type":"redirect"},"condition":{"regexFilter":"^https?://(?:www\\.)?bing\\.com/search\\?successfuledgedeflectorinstall","resourceTypes":["main_frame"]},"id":1,"priority":6},{"action":{"redirect":{"extensionPath":"/success.html"},"type":"redirect"},"condition":{"regexFilter":"^https?://(?:www\\.)?bing\\.com/#notify\\-redirect\\-extension\\-successful\\-wedge\\-install","resourceTypes":["main_frame"]},"id":2,"priority":5},{"action":{"redirect":{"regexSubstitution":"chrome-extension://lllggmgeiphnciplalhefnbpddbadfdi/redirect.html?q=\\1"},"type":"redirect"},"condition":{"regexFilter":"^https?://(?:www\\.)?bing\\.com/search\\?(?:.*&)?q=([^&]+)(?:.*&)?form=(?:WNSGPH|WNSBOX|WNSSCX|WNSFC2)","resourceTypes":["main_frame"]},"id":3,"priority":4},{"action":{"redirect":{"regexSubstitution":"https://www.google.com/search?q=\\1"},"type":"redirect"},"condition":{"regexFilter":"^https?://(?:www\\.)?bing\\.com/search\\?(?:.*&)?q=([^&]+)","resourceTypes":["main_frame"]},"id":4,"priority":3}]